pacopy/__init__.py
pacopy/_branch_switching.py
pacopy/_errors.py
pacopy/_euler_newton.py
pacopy/_natural.py
pacopy/_newton.py
pacopy-0.2.16.dist-info/METADATA
pacopy-0.2.16.dist-info/WHEEL
pacopy-0.2.16.dist-info/top_level.txt
pacopy-0.2.16.dist-info/RECORD
