Metadata-Version: 2.4
Name: pacopy
Version: 0.2.16
Summary: Numerical continuation in Python
Author-email: Nico Schlömer <nico.schloemer@gmail.com>
License-Expression: LicenseRef-Proprietary
Project-URL: Homepage, https://github.com/sigma-py/pacopy
Project-URL: Issues, https://github.com/sigma-py/pacopy/issues
Keywords: mathematics,numerical continuation,numerical methods,differential
Classifier: Development Status :: 5 - Production/Stable
Classifier: Intended Audience :: Science/Research
Classifier: Operating System :: OS Independent
Classifier: Programming Language :: Python :: 3
Classifier: Programming Language :: Python :: 3.9
Classifier: Programming Language :: Python :: 3.10
Classifier: Programming Language :: Python :: 3.11
Classifier: Programming Language :: Python :: 3.12
Classifier: Programming Language :: Python :: 3.13
Classifier: Topic :: Scientific/Engineering
Classifier: Topic :: Scientific/Engineering :: Mathematics
Requires-Python: >=3.9
Requires-Dist: rich
Requires-Dist: stonefish-license-manager>=0.5.24
Requires-Dist: x22>=0.2.1
